silicrop/__init__.py
silicrop/main.py
silicrop/assets/__init__.py
silicrop/assets/icon.png
silicrop/layout/components.py
silicrop/layout/dragdrop.py
silicrop/layout/how_to.py
silicrop/layout/styles.py
silicrop/layout/theme.py
silicrop/processing/crop.py
silicrop/processing/meplat.py
silicrop/processing/prediction.py
silicrop/processing/prediction_batch.py
silicrop/processing/rotate.py
silicrop/processing/utils.py
silicrop/training/check.py
silicrop/training/mask_resizing.py
silicrop/training/model.py
silicrop/training/test_gpu.py
silicrop-1.0.12.dist-info/licenses/LICENSE
silicrop-1.0.12.dist-info/METADATA
silicrop-1.0.12.dist-info/WHEEL
silicrop-1.0.12.dist-info/entry_points.txt
silicrop-1.0.12.dist-info/top_level.txt
silicrop-1.0.12.dist-info/RECORD
