Metadata-Version: 2.4
Name: Silicrop
Version: 1.0.12
Summary: Package for Raman TMD data processing and visualization
Author-email: Thibaut Meyer <thibaut.meyer3@gmail.com>, Thomas Blumet <xxx@gmail.com>
License: GNU GENERAL PUBLIC LICENSE
Project-URL: Homepage, https://github.com/thi-mey/silicrop
Keywords: Silicrop
Classifier: Programming Language :: Python :: 3
Classifier: Operating System :: OS Independent
Requires-Python: >=3.9
License-File: LICENSE
Requires-Dist: opencv_python
Requires-Dist: matplotlib
Requires-Dist: numpy
Requires-Dist: Pillow
Requires-Dist: PyQt5==5.15.11
Requires-Dist: PyQt5_sip==12.17.0
Requires-Dist: psutil
Requires-Dist: torch
Requires-Dist: torchvision
Requires-Dist: segmentation_models_pytorch
Dynamic: license-file
